cert_manager/__init__.py
cert_manager/__version__.py
cert_manager/_certificates.py
cert_manager/_endpoint.py
cert_manager/_helpers.py
cert_manager/acme.py
cert_manager/admin.py
cert_manager/client.py
cert_manager/domain.py
cert_manager/organization.py
cert_manager/person.py
cert_manager/report.py
cert_manager/smime.py
cert_manager/ssl.py
cert_manager-2.4.0.dist-info/LICENSE.txt
cert_manager-2.4.0.dist-info/METADATA
cert_manager-2.4.0.dist-info/WHEEL
cert_manager-2.4.0.dist-info/RECORD
