Metadata-Version: 2.1
Name: cert_manager
Version: 2.4.0
Summary: Python interface to the Sectigo Certificate Manager REST API
Home-page: https://github.com/broadinstitute/python-cert_manager.git
License: BSD-3-Clause
Keywords: sectigo,comodo,certificate
Author: Andrew Teixeira
Author-email: teixeira@broadinstitute.org
Requires-Python: >=3.7,<4.0
Classifier: License :: OSI Approved :: BSD License
Classifier: Programming Language :: Python :: 3
Classifier: Programming Language :: Python :: 3.7
Classifier: Programming Language :: Python :: 3.8
Classifier: Programming Language :: Python :: 3.9
Classifier: Programming Language :: Python :: 3.10
Classifier: Programming Language :: Python :: 3.11
Classifier: Programming Language :: Python :: 3.12
Requires-Dist: requests
Requires-Dist: toml (>=0.9,<0.11)
Project-URL: Repository, https://github.com/broadinstitute/python-cert_manager.git
